autorooms/__init__.py
autorooms/__main__.py
autorooms/bot.py
discord_autorooms-4.1.0.dist-info/LICENSE
discord_autorooms-4.1.0.dist-info/METADATA
discord_autorooms-4.1.0.dist-info/WHEEL
discord_autorooms-4.1.0.dist-info/entry_points.txt
discord_autorooms-4.1.0.dist-info/top_level.txt
discord_autorooms-4.1.0.dist-info/RECORD
