Metadata-Version: 2.1
Name: discord-autorooms
Version: 4.1.0
Summary: Zero Config Autoroom Discord Bot
Home-page: https://github.com/mikeshardmind/autorooms
Author: Michael Hall
Author-email: michael@michaelhall.tech
License: UNKNOWN
Platform: UNKNOWN
Classifier: Development Status :: 5 - Production/Stable
Classifier: Framework :: AsyncIO
Classifier: Operating System :: OS Independent
Classifier: Programming Language :: Python :: 3.6
Classifier: Programming Language :: Python :: 3.8
Classifier: Topic :: Communications :: Chat
Classifier: Natural Language :: English
Requires-Python: ~=3.8
Requires-Dist: discord.py (<2,>=1.5.1)
Provides-Extra: uvloop
Requires-Dist: uvloop ; extra == 'uvloop'
